cobib_zotero/__init__.py
cobib_zotero/importer.py
cobib_zotero/py.typed
cobib_zotero/config/__init__.py
cobib_zotero/config/config.py
cobib_zotero/man/__init__.py
cobib_zotero-0.2.0.dist-info/licenses/LICENSE.txt
cobib_zotero-0.2.0.dist-info/METADATA
cobib_zotero-0.2.0.dist-info/WHEEL
cobib_zotero-0.2.0.dist-info/entry_points.txt
cobib_zotero-0.2.0.dist-info/top_level.txt
cobib_zotero-0.2.0.dist-info/RECORD
