Metadata-Version: 2.4
Name: cobib_zotero
Version: 0.2.0
Summary: A Zotero importer plugin for coBib
Author-email: Max Rossmannek <max@rossmannek.de>
License-Expression: MIT
Project-URL: Homepage, https://gitlab.com/cobib/cobib-zotero
Project-URL: Documentation, https://cobib.gitlab.io/cobib-zotero/cobib_zotero.html
Project-URL: Repository, https://gitlab.com/cobib/cobib-zotero
Project-URL: Issues, https://gitlab.com/cobib/cobib-zotero/-/issues
Project-URL: Changelog, https://gitlab.com/cobib/cobib-zotero/-/blob/master/CHANGELOG.md
Keywords: reference-manager,citation-manager,bibliography,cli,tui,command-line,terminal,console,zotero
Classifier: Programming Language :: Python :: 3
Classifier: Programming Language :: Python :: 3.10
Classifier: Programming Language :: Python :: 3.11
Classifier: Programming Language :: Python :: 3.12
Classifier: Programming Language :: Python :: 3.13
Classifier: Programming Language :: Python :: 3.14
Classifier: Operating System :: Unix
Classifier: Environment :: Console
Classifier: Typing :: Typed
Requires-Python: >=3.10
License-File: LICENSE.txt
Requires-Dist: cobib>=6.0
Requires-Dist: pyzotero
Provides-Extra: all
Requires-Dist: cobib_zotero; extra == "all"
Provides-Extra: dev
Requires-Dist: cobib_zotero[coverage,docs,lint]; extra == "dev"
Provides-Extra: basedev
Requires-Dist: pytest~=8.4.1; extra == "basedev"
Provides-Extra: docs
Requires-Dist: cobib_zotero[basedev]; extra == "docs"
Requires-Dist: pdoc~=15.0.4; extra == "docs"
Provides-Extra: test
Requires-Dist: cobib_zotero[basedev]; extra == "test"
Requires-Dist: pytest-asyncio~=1.2.0; extra == "test"
Provides-Extra: coverage
Requires-Dist: cobib_zotero[test]; extra == "coverage"
Requires-Dist: coverage~=7.11.0; extra == "coverage"
Requires-Dist: pytest-cov~=7.0.0; extra == "coverage"
Provides-Extra: lint
Requires-Dist: cobib_zotero[basedev]; extra == "lint"
Requires-Dist: mypy~=1.18.1; extra == "lint"
Requires-Dist: ruff~=0.14.0; extra == "lint"
Requires-Dist: typos~=1.38.1; extra == "lint"
Dynamic: license-file
